scottbrian_locking/__init__.py
scottbrian_locking/__init__.pyi
scottbrian_locking/py.typed
scottbrian_locking/se_lock.py
scottbrian_locking-2.1.1.dist-info/licenses/LICENSE
scottbrian_locking-2.1.1.dist-info/METADATA
scottbrian_locking-2.1.1.dist-info/WHEEL
scottbrian_locking-2.1.1.dist-info/top_level.txt
scottbrian_locking-2.1.1.dist-info/RECORD
