Metadata-Version: 2.4
Name: scottbrian_locking
Version: 2.1.1
Summary: Exclusive and shared locking
Author-email: Scott Tuttle <sbtuttle@outlook.com>
License-Expression: MIT
Project-URL: Documentation, https://scottbrian-locking.readthedocs.io/en/latest/
Project-URL: Source, https://github.com/ScottBrian/scottbrian_locking.git
Keywords: lock,blocking
Classifier: Development Status :: 5 - Production/Stable
Classifier: Intended Audience :: Developers
Classifier: Topic :: Software Development :: Libraries :: Python Modules
Classifier: Programming Language :: Python :: 3
Classifier: Programming Language :: Python :: 3.12
Classifier: Programming Language :: Python :: 3.13
Classifier: Operating System :: Microsoft :: Windows :: Windows 10
Requires-Python: ~=3.12
License-File: LICENSE
Requires-Dist: typing_extensions~=4.11
Requires-Dist: scottbrian-utils~=5.0
Dynamic: license-file
